{
	"requestParams": [
		{
			"subParams": [
				{
					"name": "order_id",
					"type": "Number",
					"description": "大麦订单号",
					"required": true
				}
			],
			"name": "param",
			"type": "MoaUnlockTicketParam",
			"description": "库存释放入参",
			"required": true
		}
	],
	"responseParams": [
		{
			"subParams": [
				{
					"name": "message",
					"type": "String",
					"description": "message"
				},
				{
					"subParams": [
						{
							"name": "order_id",
							"type": "Number",
							"description": "订单id"
						}
					],
					"name": "model",
					"type": "UnLockTicketResponse",
					"description": "数据对象"
				},
				{
					"name": "code",
					"type": "Number",
					"description": "结果code，0代表成功，负数代表异常情况"
				},
				{
					"name": "success",
					"type": "Boolean",
					"description": "是否成功，true:成功，false:失败"
				}
			],
			"name": "result",
			"type": "MxResult",
			"description": "返回结果集"
		}
	],
	"name": "alibaba.damai.maitix.order.cancel",
	"apiChineseName": "大麦-库存释放",
	"description": "库存释放",
	"id": 38142
}