{
	"requestParams": [
		{
			"name": "product_id",
			"type": "Number",
			"description": "产品数字ID"
		},
		{
			"name": "sku_id",
			"type": "Number",
			"description": "SKU ID"
		}
	],
	"responseParams": [
		{
			"subParams": [
				{
					"name": "success",
					"type": "Boolean",
					"description": "执行结果"
				},
				{
					"name": "module",
					"type": "String",
					"description": "库存数量"
				},
				{
					"name": "error_message",
					"type": "String",
					"description": "错误码"
				},
				{
					"name": "error_code",
					"type": "String",
					"description": "错误码"
				}
			],
			"name": "result",
			"type": "ResultDto",
			"description": "异步获取历史数据接口返回结果"
		}
	],
	"name": "tmall.supplychain.channel.product.quantity.get",
	"apiChineseName": "渠道库存查询接口",
	"description": "渠道库存查询接口",
	"id": 49549
}