{
	"name": "taobao.files.get",
	"apiChineseName": "业务文件获取",
	"description": "获取业务方暂存给ISV的文件列表",
	"requestParams": [
		{
			"name": "start_date",
			"type": "Date",
			"description": "搜索开始时间",
			"required": true
		},
		{
			"name": "end_date",
			"type": "Date",
			"description": "搜索结束时间",
			"required": true
		},
		{
			"name": "status",
			"type": "Number",
			"description": "下载链接状态。1:未下载。2:已下载"
		}
	],
	"responseParams": [
		{
			"name": "results",
			"type": "TopDownloadRecordDo []",
			"description": "results",
			"subParams": [
				{
					"name": "url",
					"type": "String",
					"description": "下载链接",
					"required": true
				},
				{
					"name": "created",
					"type": "Date",
					"description": "文件创建时间",
					"required": true
				},
				{
					"name": "status",
					"type": "Number",
					"description": "下载链接状态。1:未下载。2:已下载",
					"required": true
				}
			]
		}
	]
}